arcade_vercel_api/__init__.py
arcade_vercel_api/tools/__init__.py
arcade_vercel_api/tools/request_body_schemas.py
arcade_vercel_api/wrapper_tools/AcceptProjectTransfer.json
arcade_vercel_api/wrapper_tools/AddEdgeConfigToken.json
arcade_vercel_api/wrapper_tools/AddNewDomainVercel.json
arcade_vercel_api/wrapper_tools/AddProjectDomain.json
arcade_vercel_api/wrapper_tools/AddProjectMember.json
arcade_vercel_api/wrapper_tools/AdvanceRolloutStage.json
arcade_vercel_api/wrapper_tools/CancelDeployment.json
arcade_vercel_api/wrapper_tools/CheckDomainAvailability.json
arcade_vercel_api/wrapper_tools/CheckDomainAvailabilityBulk.json
arcade_vercel_api/wrapper_tools/CheckDomainTransferStatus.json
arcade_vercel_api/wrapper_tools/CheckRemoteCachingStatus.json
arcade_vercel_api/wrapper_tools/CheckTeamAccessStatus.json
arcade_vercel_api/wrapper_tools/ConnectIntegrationResourceToProject.json
arcade_vercel_api/wrapper_tools/CreateAccessGroup.json
arcade_vercel_api/wrapper_tools/CreateAccessGroupProject.json
arcade_vercel_api/wrapper_tools/CreateAuthToken.json
arcade_vercel_api/wrapper_tools/CreateCustomEnvironment.json
arcade_vercel_api/wrapper_tools/CreateDnsRecord.json
arcade_vercel_api/wrapper_tools/CreateEdgeConfig.json
arcade_vercel_api/wrapper_tools/CreateExperimentationItems.json
arcade_vercel_api/wrapper_tools/CreateFirewallBypassRule.json
arcade_vercel_api/wrapper_tools/CreateIntegrationLogDrain.json
arcade_vercel_api/wrapper_tools/CreateIntegrationStore.json
arcade_vercel_api/wrapper_tools/CreateNewDeploymentCheck.json
arcade_vercel_api/wrapper_tools/CreateNewProject.json
arcade_vercel_api/wrapper_tools/CreateProjectEnvironmentVariables.json
arcade_vercel_api/wrapper_tools/CreateVercelDeployment.json
arcade_vercel_api/wrapper_tools/CreateVercelTeam.json
arcade_vercel_api/wrapper_tools/CreateVercelWebhook.json
arcade_vercel_api/wrapper_tools/DeleteAccessGroup.json
arcade_vercel_api/wrapper_tools/DeleteAccessGroupProject.json
arcade_vercel_api-1.0.0.dist-info/METADATA
arcade_vercel_api-1.0.0.dist-info/WHEEL
arcade_vercel_api-1.0.0.dist-info/entry_points.txt
arcade_vercel_api-1.0.0.dist-info/licenses/LICENSE
arcade_vercel_api-1.0.0.dist-info/RECORD
